haerae_evaluation_toolkit-0.1.0.dist-info/licenses/LICENSE
llm_eval/__init__.py
llm_eval/analysis.py
llm_eval/evaluator.py
llm_eval/hret.py
llm_eval/runner.py
llm_eval/datasets/__init__.py
llm_eval/datasets/aime2025.py
llm_eval/datasets/base.py
llm_eval/datasets/benchhub.py
llm_eval/datasets/click.py
llm_eval/datasets/dataset_loader.py
llm_eval/datasets/haerae.py
llm_eval/datasets/hrc.py
llm_eval/datasets/hrm8k.py
llm_eval/datasets/k2_eval.py
llm_eval/datasets/kbl.py
llm_eval/datasets/kmmlu.py
llm_eval/datasets/kormedqa.py
llm_eval/datasets/kudge.py
llm_eval/evaluation/__init__.py
llm_eval/evaluation/base.py
llm_eval/evaluation/llm_judge.py
llm_eval/evaluation/log_prob.py
llm_eval/evaluation/math_eval.py
llm_eval/evaluation/partial_match.py
llm_eval/evaluation/string_match.py
llm_eval/internal/benchhub_info.py
llm_eval/models/__init__.py
llm_eval/models/base.py
llm_eval/models/huggingface_backend.py
llm_eval/models/huggingface_judge.py
llm_eval/models/huggingface_reward.py
llm_eval/models/litellm_backend.py
llm_eval/models/litellm_judge.py
llm_eval/models/multi.py
llm_eval/models/openai_backend.py
llm_eval/models/openai_judge.py
llm_eval/models/vllm_backend.py
llm_eval/scaling_methods/__init__.py
llm_eval/scaling_methods/base.py
llm_eval/scaling_methods/beam_search.py
llm_eval/scaling_methods/best_of_n.py
llm_eval/scaling_methods/self_consistency.py
llm_eval/test/__init__.py
llm_eval/test/test_datasets.py
llm_eval/test/test_evaluations.py
llm_eval/test/test_evaluator_config.py
llm_eval/test/test_generic_file_dataset.py
llm_eval/test/test_scaling.py
llm_eval/utils/__init__.py
llm_eval/utils/logging.py
llm_eval/utils/metrics.py
llm_eval/utils/prompt_template.py
llm_eval/utils/util.py
haerae_evaluation_toolkit-0.1.0.dist-info/METADATA
haerae_evaluation_toolkit-0.1.0.dist-info/WHEEL
haerae_evaluation_toolkit-0.1.0.dist-info/top_level.txt
haerae_evaluation_toolkit-0.1.0.dist-info/RECORD
