Metadata-Version: 2.4
Name: haerae-evaluation-toolkit
Version: 0.1.0
Summary: A comprehensive, standardized validation toolkit for Korean Large Language Models (LLMs).
Author-email: Hanwool Lee <gksdnf424@gmail.com>
License-Expression: Apache-2.0
Project-URL: Homepage, https://github.com/HAE-RAE/haerae-evaluation-toolkit
Project-URL: Repository, https://github.com/HAE-RAE/haerae-evaluation-toolkit
Project-URL: Issues, https://github.com/HAE-RAE/haerae-evaluation-toolkit/issues
Project-URL: Documentation, https://github.com/HAE-RAE/haerae-evaluation-toolkit/tree/main/docs
Project-URL: Bug Reports, https://github.com/HAE-RAE/haerae-evaluation-toolkit/issues
Project-URL: Source Code, https://github.com/HAE-RAE/haerae-evaluation-toolkit
Keywords: llm,evaluation,korean,nlp,benchmark,hret
Classifier: Programming Language :: Python :: 3.10
Classifier: Programming Language :: Python :: 3.11
Classifier: Programming Language :: Python :: 3.12
Classifier: Operating System :: OS Independent
Classifier: Intended Audience :: Developers
Classifier: Intended Audience :: Science/Research
Classifier: Topic :: Scientific/Engineering :: Artificial Intelligence
Classifier: Topic :: Text Processing :: Linguistic
Classifier: Development Status :: 4 - Beta
Requires-Python: >=3.10
License-File: LICENSE
Requires-Dist: transformers>=4.20.0
Requires-Dist: torch>=2.0.0
Requires-Dist: openai<1.100.0,>=1.0.0
Requires-Dist: datasets>=3.2.0
Requires-Dist: litellm>=1.75.0
Requires-Dist: math-verify>=0.1.0
Requires-Dist: pandas>=1.5.0
Requires-Dist: tqdm>=4.64.0
Requires-Dist: langdetect>=1.0.9
Requires-Dist: httpx>=0.24.0
Requires-Dist: vllm>=0.4.0
Requires-Dist: accelerate>=0.20.0
Requires-Dist: spacy>=3.4.0
Requires-Dist: scikit-learn>=1.1.0
Provides-Extra: dev
Requires-Dist: pre-commit==4.0.1; extra == "dev"
Requires-Dist: pytest>=7.3.0; extra == "dev"
Provides-Extra: test
Requires-Dist: pytest>=7.3.0; extra == "test"
Requires-Dist: pytest-mock>=3.10.0; extra == "test"
Dynamic: license-file
